<?xml version="1.0" ?>
<Records>
  <Record>
    <ClaimNumber>SL7654337</ClaimNumber>
    <PolicyNumber>PN1122350</PolicyNumber>
    <InsuredName>Alexander Martin</InsuredName>
    <LossDate>2024-03-26</LossDate>
    <GlassRepairCost>290.50</GlassRepairCost>
    <GlassType>Side Window</GlassType>
    <VendorInvoiceNumber>INV775560</VendorInvoiceNumber>
    <VehicleMake>Dodge</VehicleMake>
    <VehicleModel>Charger</VehicleModel>
    <VehicleYear>2019</VehicleYear>
    <CustomerPhone>555-123-4583</CustomerPhone>
    <DamageDescription>Complete break, driver rear</DamageDescription>
  </Record>
</Records>
